trellisdata/__init__.py
trellisdata/database_query.py
trellisdata/database_trigger.py
trellisdata/job_launcher.py
trellisdata/messages.py
trellisdata/operation_grapher.py
trellisdata/utils.py
trellisdata-0.1.26.dist-info/LICENSE
trellisdata-0.1.26.dist-info/METADATA
trellisdata-0.1.26.dist-info/WHEEL
trellisdata-0.1.26.dist-info/top_level.txt
trellisdata-0.1.26.dist-info/RECORD
