Metadata-Version: 2.1
Name: trellisdata
Version: 0.1.26
Summary: Tools for implementing a Trellis data management system
Home-page: https://github.com/StanfordBioinformatics/trellisdata
Author: Paul Billing-Ross
Author-email: pbilling@stanford.edu
Project-URL: ReadTheDocs, https://trellis-data-management.readthedocs.io
Classifier: Programming Language :: Python :: 3
Classifier: License :: OSI Approved :: MIT License
Requires-Python: >=3.6
License-File: LICENSE
Requires-Dist: neo4j (>=4.4.0)
Requires-Dist: anytree (>=2.8.0)
